{
  "name": "Mapping Extensions",
  "description": "This adds a host of new things you can do with your maps as a mapper, and allows you to play said maps as a player. An update of the port of the PC original mod by Kyle 1413. Previously maintained by zoller27osu.",
  "id": "MappingExtensions",
  "version": "0.21.3",
  "author": "StackDoubleFlow, rxzz0, rcelyte",
  "authorIcon": "https://avatars.githubusercontent.com/u/25163630?v=4",
  "modloader": "QuestLoader",
  "download": "https://github.com/rcelyte/MappingExtensions/releases/download/0.21.3/MappingExtensions.qmod",
  "dependencies": [],
  "isLibrary": false,
  "source": "https://github.com/rcelyte/MappingExtensions/",
  "cover": "http://mods.bsquest.xyz/covers/0f042efcddb27f8be53a0e6d49e32ba30c973e59.png",
  "ogCover": "http://mods.bsquest.xyz/covers/originals/0f042efcddb27f8be53a0e6d49e32ba30c973e59.png",
  "funding": [],
  "website": "https://github.com/rcelyte/MappingExtensions/",
  "hash": "330ed380bd6ca07b6313cac17fc7f4ecc56c2b50",
  "description_zh": null,
  "name_zh": null
}