{
  "name": "MoreButtons",
  "description": "Overloads your keyboard!",
  "id": "morebuttons",
  "version": "1.0.4",
  "author": "Metalit",
  "authorIcon": "https://avatars.githubusercontent.com/u/48568911?v=4",
  "modloader": "Scotland2",
  "download": "https://github.com/Metalit/MoreButtons/releases/download/v1.0.4/MoreButtons.qmod",
  "dependencies": [
    {
      "id": "beatsaber-hook",
      "version": "^6.4.0"
    },
    {
      "id": "paper2_scotland2",
      "version": "^4.6.1"
    }
  ],
  "isLibrary": false,
  "source": "https://github.com/Metalit/MoreButtons/",
  "cover": null,
  "ogCover": null,
  "funding": [],
  "website": "https://github.com/Metalit/MoreButtons/",
  "hash": "a5d205ce39d27b54befc80627eb68c9891f7bae9",
  "description_zh": "增强游戏里的键盘！",
  "name_zh": "更多按钮"
}