{
  "name": "SlowResume",
  "description": "Allows you to change how long the countdown takes to resume when paused. Disables score submission if the amount of time is increased, since this makes pausing an easier method to get back your stamina.\r\n\r\nTo change the amount of time, go to the Settings Icon in the main menu -> Mod Settings -> SlowResume.\r\n\r\nThis mod was commissioned",
  "id": "slow-resume",
  "version": "0.1.1",
  "author": "Laurie",
  "authorIcon": "https://avatars.githubusercontent.com/u/44222319?v=4",
  "modloader": "QuestLoader",
  "download": "https://github.com/Lauriethefish/SlowResume/releases/download/0.1.1/slow-resume_v0.1.1.zip",
  "dependencies": [],
  "isLibrary": false,
  "source": "https://github.com/Lauriethefish/SlowResume/",
  "cover": "http://mods.bsquest.xyz/covers/a3b38537f9fd781802835fa7c85042de3adcb60e.png",
  "ogCover": "http://mods.bsquest.xyz/covers/originals/a3b38537f9fd781802835fa7c85042de3adcb60e.png",
  "funding": [],
  "website": null,
  "hash": "e17f2f20b28a86c679d02249c592cece624feee2",
  "description_zh": null,
  "name_zh": null
}