{
  "name": "SongInfoPlus",
  "description": "View extra song info by clicking the cover art",
  "id": "SongInfoPlus",
  "version": "1.0.2",
  "author": "OptimusChen",
  "authorIcon": "https://avatars.githubusercontent.com/u/69561711?v=4",
  "modloader": "QuestLoader",
  "download": "https://github.com/OptimusChen/SongInfoPlus/releases/download/v1.0.2/SongInfoPlus_v1.0.2.qmod",
  "dependencies": [],
  "isLibrary": false,
  "source": "https://github.com/OptimusChen/SongInfoPlus/",
  "cover": null,
  "ogCover": null,
  "funding": [],
  "website": null,
  "hash": "0ee295f0ae349ca2dd96d32c9a2ac08e407feac3",
  "description_zh": null,
  "name_zh": null
}